{
  "id": "18005",
  "name": "Ibrahim bin 'Abdullah bin 'Abd al-Qari' إبراهيم بن عبد الله بن عبد القاري",
  "full_name": "Ibrahim bin 'Abdullah bin 'Abd al-Qari' إبراهيم بن عبد الله بن عبد القاري",
  "grade": "Follower(Tabi') [3rd Generation]",
  "biography": {
    "birth": {
      "date_hijri": "NA",
      "date_gregorian": "NA",
      "date_display": null,
      "place": "NA"
    },
    "death": {
      "date_hijri": "100",
      "date_gregorian": "NA",
      "date_display": null,
      "place": "",
      "reason": "Natural"
    },
    "places_of_stay": [
      "Medina"
    ],
    "area_of_interest": [
      "Narrator[Grade:Maqbool] [ س  -  مقبول ]"
    ],
    "tags": [
      "al-Qari",
      "Madni"
    ]
  },
  "parents": [],
  "spouses": [],
  "siblings": [],
  "children": [],
  "teachers": [
    {
      "id": "17",
      "name": "ibn Abbas ( عبد الله بن العباس بن عبد المطلب الحبر ( رضي الله عنه",
      "grade": "Comp.(RA) [1st Generation]"
    },
    {
      "id": "11679",
      "name": "al-J'ad bin 'Abdur Rahman الجعد/الجعيد بن عبد الرحمن بن أوس",
      "grade": "Follower(Tabi') [5th generation]"
    }
  ],
  "students": [],
  "hadiths": [],
  "total_hadiths": 0
}