{
  "id": "18601",
  "name": "'Abdul Hameed bin al-Mndhr عبد الحميد بن المنذر بن الجارود العبدي",
  "full_name": "'Abdul Hameed bin al-Mndhr عبد الحميد بن المنذر بن الجارود العبدي",
  "grade": "Follower(Tabi') [5th generation]",
  "reliability_grade": "Thiqah",
  "biography": {
    "birth": {
      "date_hijri": "NA",
      "date_gregorian": "NA",
      "date_display": null,
      "place": "NA"
    },
    "death": {
      "date_hijri": "NA",
      "date_gregorian": "NA",
      "date_display": null,
      "place": "",
      "reason": "Natural"
    },
    "places_of_stay": [
      "NA"
    ],
    "area_of_interest": [
      "Narrator[Grade:Thiqah] [ ق  -  ثقة ]"
    ],
    "tags": [
      "al-'Abdi"
    ],
    "area_of_interest_display": [
      {
        "en": "Narrator[Grade:Thiqah] [ ق  -  ثقة ]",
        "ar": "Narrator[Grade:Thiqah] [ ق  -  ثقة ]",
        "ckb": "Narrator[Grade:Thiqah] [ ق  -  ثقة ]"
      }
    ],
    "places_of_stay_display": [
      {
        "en": "NA",
        "ar": "NA",
        "ckb": "NA"
      }
    ],
    "tags_display": [
      {
        "en": "al-'Abdi",
        "ar": "al-'Abdi",
        "ckb": "al-'Abdi"
      }
    ]
  },
  "parents": [],
  "spouses": [],
  "siblings": [],
  "children": [],
  "teachers": [
    {
      "id": "19",
      "name": "Anas bin Malik ( أنس بن مالك بن النضر ( رضي الله عنه",
      "grade": "Comp.(RA) [1st Generation]",
      "grade_display": {
        "en": "Companion (RA) [1st Generation]",
        "ar": "صحابي (رضي الله عنه) [الجيل الأول]",
        "ckb": "هاوەڵ (رەزای خوای لێبێت) [نەوەی یەكەم]"
      }
    }
  ],
  "students": [
    {
      "id": "11038",
      "name": "Anas bin Sirin أنس بن سيرين الأنصاري",
      "grade": "Follower(Tabi') [3rd Generation]",
      "grade_display": {
        "en": "Follower (Tabi') [3rd Generation]",
        "ar": "تابعي [الجيل الثالث]",
        "ckb": "شوێنكەوتوو (تابعی) [نەوەی سێیەم]"
      }
    }
  ],
  "hadiths": [],
  "total_hadiths": 0,
  "grade_display": {
    "en": "Follower (Tabi') [5th Generation]",
    "ar": "تابعي [الجيل الخامس]",
    "ckb": "شوێنكەوتوو (تابعی) [نەوەی پێنجەم]"
  }
}