{
  "id": "19893",
  "name": "'Aabadh bin Nsy عبادة بن نسي",
  "full_name": "'Aabadh bin Nsy عبادة بن نسي",
  "grade": "Follower(Tabi') [3rd Generation]",
  "reliability_grade": "Thiqah",
  "biography": {
    "birth": {
      "date_hijri": "NA",
      "date_gregorian": "NA",
      "date_display": null,
      "place": "NA"
    },
    "death": {
      "date_hijri": "110",
      "date_gregorian": "NA",
      "date_display": null,
      "place": "",
      "reason": "Natural"
    },
    "places_of_stay": [
      "Syria"
    ],
    "area_of_interest": [
      "Narrator[Grade:Thiqah] [ 4  -  ثقة ]"
    ],
    "tags": [
      "al-Kundi",
      "Judge",
      "al-Shami"
    ],
    "area_of_interest_display": [
      {
        "en": "Narrator[Grade:Thiqah] [ 4  -  ثقة ]",
        "ar": "Narrator[Grade:Thiqah] [ 4  -  ثقة ]",
        "ckb": "Narrator[Grade:Thiqah] [ 4  -  ثقة ]"
      }
    ],
    "places_of_stay_display": [
      {
        "en": "Syria",
        "ar": "الشام",
        "ckb": "شام"
      }
    ],
    "tags_display": [
      {
        "en": "al-Kundi",
        "ar": "al-Kundi",
        "ckb": "al-Kundi"
      },
      {
        "en": "Judge (Qadi)",
        "ar": "قاضي",
        "ckb": "دادوەر"
      },
      {
        "en": "al-Shami",
        "ar": "al-Shami",
        "ckb": "al-Shami"
      }
    ]
  },
  "parents": [],
  "spouses": [],
  "siblings": [],
  "children": [],
  "teachers": [
    {
      "id": "389",
      "name": "Shadad bin Aus bin Thabit ( شداد بن أوس بن ثابت ( رضي الله عنه",
      "grade": "Comp.(RA) [1st Generation]",
      "grade_display": {
        "en": "Companion (RA) [1st Generation]",
        "ar": "صحابي (رضي الله عنه) [الجيل الأول]",
        "ckb": "هاوەڵ (رەزای خوای لێبێت) [نەوەی یەكەم]"
      }
    },
    {
      "id": "40",
      "name": "'Ubada bin As-Samit ( عبادة بن الصامت بن قيس بن أصرم ( رضي الله عنه",
      "grade": "Comp.(RA) [1st Generation]",
      "grade_display": {
        "en": "Companion (RA) [1st Generation]",
        "ar": "صحابي (رضي الله عنه) [الجيل الأول]",
        "ckb": "هاوەڵ (رەزای خوای لێبێت) [نەوەی یەكەم]"
      }
    },
    {
      "id": "37",
      "name": "Abu al-Darda ( أبو الدرداء عويمر بن زيد بن قيس الأنصاري ( رضي الله عنه",
      "grade": "Comp.(RA) [1st Generation]",
      "grade_display": {
        "en": "Companion (RA) [1st Generation]",
        "ar": "صحابي (رضي الله عنه) [الجيل الأول]",
        "ckb": "هاوەڵ (رەزای خوای لێبێت) [نەوەی یەكەم]"
      }
    },
    {
      "id": "5152",
      "name": "'Abdur Rahman bin Ghnm ( عبد الرحمن بن غنم ( رضي الله عنه",
      "grade": "Comp.(RA) [1st Generation]",
      "grade_display": {
        "en": "Companion (RA) [1st Generation]",
        "ar": "صحابي (رضي الله عنه) [الجيل الأول]",
        "ckb": "هاوەڵ (رەزای خوای لێبێت) [نەوەی یەكەم]"
      }
    },
    {
      "id": "149",
      "name": "Khabbab ibn al-Aratt ( خباب بن الأرت ( رضي الله عنه",
      "grade": "Comp.(RA) [1st Generation]",
      "grade_display": {
        "en": "Companion (RA) [1st Generation]",
        "ar": "صحابي (رضي الله عنه) [الجيل الأول]",
        "ckb": "هاوەڵ (رەزای خوای لێبێت) [نەوەی یەكەم]"
      }
    },
    {
      "id": "17002",
      "name": "al-Aswad bin Tha'lbah al-Kndy الأسود بن ثعلبة الكندي الشامي",
      "grade": "Follower(Tabi') [3rd Generation]",
      "grade_display": {
        "en": "Follower (Tabi') [3rd Generation]",
        "ar": "تابعي [الجيل الثالث]",
        "ckb": "شوێنكەوتوو (تابعی) [نەوەی سێیەم]"
      }
    },
    {
      "id": "4062",
      "name": "Ubayy bin 'Umara ( أبي بن عمارة ( رضي الله عنه",
      "grade": "Comp.(RA) [1st Generation]",
      "grade_display": {
        "en": "Companion (RA) [1st Generation]",
        "ar": "صحابي (رضي الله عنه) [الجيل الأول]",
        "ckb": "هاوەڵ (رەزای خوای لێبێت) [نەوەی یەكەم]"
      }
    },
    {
      "id": "3205",
      "name": "Junadah bin Abi Umayya ( جنادة بن أبي أمية ( رضي الله عنه",
      "grade": "Comp.(RA) [1st Generation]",
      "grade_display": {
        "en": "Companion (RA) [1st Generation]",
        "ar": "صحابي (رضي الله عنه) [الجيل الأول]",
        "ckb": "هاوەڵ (رەزای خوای لێبێت) [نەوەی یەكەم]"
      }
    },
    {
      "id": "4052",
      "name": "Ka'b bin 'Ajra al-Salmi, al-Ansari ( كعب بن عجرة الأنصاري ( رضي الله عنه",
      "grade": "Comp.(RA) [1st Generation]",
      "grade_display": {
        "en": "Companion (RA) [1st Generation]",
        "ar": "صحابي (رضي الله عنه) [الجيل الأول]",
        "ckb": "هاوەڵ (رەزای خوای لێبێت) [نەوەی یەكەم]"
      }
    }
  ],
  "students": [
    {
      "id": "19839",
      "name": "Bard bin Sinan برد بن سنان",
      "grade": "Follower(Tabi') [5th generation]",
      "grade_display": {
        "en": "Follower (Tabi') [5th Generation]",
        "ar": "تابعي [الجيل الخامس]",
        "ckb": "شوێنكەوتوو (تابعی) [نەوەی پێنجەم]"
      }
    },
    {
      "id": "19947",
      "name": "al-Mughira bin Ziyad al-Bjly المغيرة بن زياد البجلي أبو هشام",
      "grade": "Follower(Tabi') [6th generation]",
      "grade_display": {
        "en": "Follower (Tabi') [6th Generation]",
        "ar": "تابعي [الجيل السادس]",
        "ckb": "شوێنكەوتوو (تابعی) [نەوەی شەشەم]"
      }
    },
    {
      "id": "28326",
      "name": "'Abdur Rahman bin Ziyad عبد الرحمن بن زياد بن أنعم",
      "grade": "Succ. (Taba' Tabi') [7th generation]",
      "grade_display": {
        "en": "Successor (Taba' Tabi') [7th Generation]",
        "ar": "تابع التابعين [الجيل السابع]",
        "ckb": "شوێنكەوتووی شوێنكەوتوو [نەوەی حەوتەم]"
      }
    },
    {
      "id": "18069",
      "name": "Ayoub bin Qtn أيوب بن قطن",
      "grade": "Follower(Tabi') [5th generation]",
      "grade_display": {
        "en": "Follower (Tabi') [5th Generation]",
        "ar": "تابعي [الجيل الخامس]",
        "ckb": "شوێنكەوتوو (تابعی) [نەوەی پێنجەم]"
      }
    },
    {
      "id": "11582",
      "name": "al-Hasan bin Dhkwan Abu الحسن بن ذكوان أبو سلمة",
      "grade": "Follower(Tabi') [6th generation]",
      "grade_display": {
        "en": "Follower (Tabi') [6th Generation]",
        "ar": "تابعي [الجيل السادس]",
        "ckb": "شوێنكەوتوو (تابعی) [نەوەی شەشەم]"
      }
    },
    {
      "id": "14262",
      "name": "'Utba bin Hameed al-Dby عتبة بن حميد الضبي أبو معاذ",
      "grade": "Follower(Tabi') [6th generation]",
      "grade_display": {
        "en": "Follower (Tabi') [6th Generation]",
        "ar": "تابعي [الجيل السادس]",
        "ckb": "شوێنكەوتوو (تابعی) [نەوەی شەشەم]"
      }
    },
    {
      "id": "17064",
      "name": "Mnyr bin al-Zubair al-Shamy Abu منير بن الزبير",
      "grade": "Follower(Tabi') [6th generation]",
      "grade_display": {
        "en": "Follower (Tabi') [6th Generation]",
        "ar": "تابعي [الجيل السادس]",
        "ckb": "شوێنكەوتوو (تابعی) [نەوەی شەشەم]"
      }
    },
    {
      "id": "19928",
      "name": "'Utba bin Abi Hkym عتبة بن أبي حكيم الهمداني",
      "grade": "Follower(Tabi') [6th generation]",
      "grade_display": {
        "en": "Follower (Tabi') [6th Generation]",
        "ar": "تابعي [الجيل السادس]",
        "ckb": "شوێنكەوتوو (تابعی) [نەوەی شەشەم]"
      }
    },
    {
      "id": "24139",
      "name": "Rja'a bin Abi Salmah رجاء بن أبي سلمة مهران",
      "grade": "Succ. (Taba' Tabi') [7th generation]",
      "grade_display": {
        "en": "Successor (Taba' Tabi') [7th Generation]",
        "ar": "تابع التابعين [الجيل السابع]",
        "ckb": "شوێنكەوتووی شوێنكەوتوو [نەوەی حەوتەم]"
      }
    },
    {
      "id": "18320",
      "name": "Zayd bin Aymn زيد بن أيمن",
      "grade": "Follower(Tabi') [6th generation]",
      "grade_display": {
        "en": "Follower (Tabi') [6th Generation]",
        "ar": "تابعي [الجيل السادس]",
        "ckb": "شوێنكەوتوو (تابعی) [نەوەی شەشەم]"
      }
    },
    {
      "id": "11169",
      "name": "Sa'id bin Abi Hilal سعيد بن أبي هلال الليثي",
      "grade": "Follower(Tabi') [6th generation]",
      "grade_display": {
        "en": "Follower (Tabi') [6th Generation]",
        "ar": "تابعي [الجيل السادس]",
        "ckb": "شوێنكەوتوو (تابعی) [نەوەی شەشەم]"
      }
    }
  ],
  "hadiths": [],
  "total_hadiths": 0,
  "grade_display": {
    "en": "Follower (Tabi') [3rd Generation]",
    "ar": "تابعي [الجيل الثالث]",
    "ckb": "شوێنكەوتوو (تابعی) [نەوەی سێیەم]"
  }
}