{
  "id": "21522",
  "name": "al-Rabi' bin Abi Rashid الربيع بن أبي راشد",
  "full_name": "al-Rabi' bin Abi Rashid الربيع بن أبي راشد",
  "grade": "Succ. (Taba' Tabi')",
  "reliability_grade": "Thiqah",
  "biography": {
    "birth": {
      "date_hijri": "NA",
      "date_gregorian": "NA",
      "date_display": null,
      "place": "NA"
    },
    "death": {
      "date_hijri": "NA",
      "date_gregorian": "NA",
      "date_display": null,
      "place": "",
      "reason": "Natural"
    },
    "places_of_stay": [
      "Kufa"
    ],
    "area_of_interest": [
      "Narrator[Grade:Thiqah]"
    ],
    "tags": [
      "Kufi"
    ]
  },
  "parents": [],
  "spouses": [],
  "siblings": [
    {
      "id": "11327",
      "name": "Jami' bin Abi Rashid جامع بن أبي راشد الكاهلي",
      "grade": "Follower(Tabi') [5th generation]"
    }
  ],
  "children": [],
  "teachers": [],
  "students": [
    {
      "id": "20012",
      "name": "Sufyan bin Sa‘id Ath-Thawri سفيان الثوري",
      "grade": "Succ. (Taba' Tabi') [7th generation]"
    }
  ],
  "hadiths": [],
  "total_hadiths": 0
}