{
  "id": "24213",
  "name": "Safwan bin Hbyrh صفوان بن هبيرة",
  "full_name": "Safwan bin Hbyrh صفوان بن هبيرة",
  "grade": "Succ. (Taba' Tabi') [9th generation]",
  "reliability_grade": "Maqbool",
  "biography": {
    "birth": {
      "date_hijri": "NA",
      "date_gregorian": "NA",
      "date_display": null,
      "place": "NA"
    },
    "death": {
      "date_hijri": "NA",
      "date_gregorian": "NA",
      "date_display": null,
      "place": "",
      "reason": "Natural"
    },
    "places_of_stay": [
      "al-Basra"
    ],
    "area_of_interest": [
      "Narrator[Grade:Maqbool] [ ق  -  لين الحديث ]"
    ],
    "tags": [
      "al-Basri"
    ],
    "area_of_interest_display": [
      {
        "en": "Narrator[Grade:Maqbool] [ ق  -  لين الحديث ]",
        "ar": "Narrator[Grade:Maqbool] [ ق  -  لين الحديث ]",
        "ckb": "Narrator[Grade:Maqbool] [ ق  -  لين الحديث ]"
      }
    ],
    "places_of_stay_display": [
      {
        "en": "Basra",
        "ar": "البصرة",
        "ckb": "بەسرە"
      }
    ],
    "tags_display": [
      {
        "en": "al-Basri",
        "ar": "al-Basri",
        "ckb": "al-Basri"
      }
    ]
  },
  "parents": [],
  "spouses": [],
  "siblings": [],
  "children": [],
  "teachers": [
    {
      "id": "14399",
      "name": "Nwh bin Rabi'ya al-Ansari نوح بن ربيعة الأنصاري مولاهم أبو مكين",
      "grade": "Follower(Tabi') [6th generation]",
      "grade_display": {
        "en": "Follower (Tabi') [6th Generation]",
        "ar": "تابعي [الجيل السادس]",
        "ckb": "شوێنكەوتوو (تابعی) [نەوەی شەشەم]"
      }
    },
    {
      "id": "11070",
      "name": "Ibn Jurayj ابن جريج",
      "grade": "Follower(Tabi') [6th generation]",
      "grade_display": {
        "en": "Follower (Tabi') [6th Generation]",
        "ar": "تابعي [الجيل السادس]",
        "ckb": "شوێنكەوتوو (تابعی) [نەوەی شەشەم]"
      }
    }
  ],
  "students": [
    {
      "id": "30115",
      "name": "al-Hasan bin 'Ali al-Halwani الحسن بن علي الخلال الحلواني",
      "grade": "3rd Century AH [11th generation]",
      "grade_display": {
        "en": "3rd Century AH [11th Generation]",
        "ar": "القرن الثالث الهجري [الجيل الحادي عشر]",
        "ckb": "سەدەی سێیەمی كۆچی [نەوەی یازدەیەم]"
      }
    },
    {
      "id": "30023",
      "name": "Muhammad bin Yahya bin Faris al-Dhahli محمد بن يحيى بن فارس الذهلي",
      "grade": "3rd Century AH [11th generation]",
      "grade_display": {
        "en": "3rd Century AH [11th Generation]",
        "ar": "القرن الثالث الهجري [الجيل الحادي عشر]",
        "ckb": "سەدەی سێیەمی كۆچی [نەوەی یازدەیەم]"
      }
    },
    {
      "id": "34140",
      "name": "'Abdul Malik bin Muhammad bin 'Abdullah عبد الملك بن محمد أبو قلابة الرقاشي",
      "grade": "3rd Century AH [11th generation]",
      "grade_display": {
        "en": "3rd Century AH [11th Generation]",
        "ar": "القرن الثالث الهجري [الجيل الحادي عشر]",
        "ckb": "سەدەی سێیەمی كۆچی [نەوەی یازدەیەم]"
      }
    }
  ],
  "hadiths": [
    {
      "id": "sunan-ibn-majah-1506",
      "hadith_no": "1506",
      "source": "Sunan Ibn Majah",
      "chapter": "Chapters Regarding Funerals - كتاب الجنائز",
      "chapter_no": "6",
      "text_ar": "حدثنا الحسن بن علي الخلال، حدثنا صفوان بن هبيرة، حدثنا أبو مكين، عن عكرمة، عن ابن عباس، أن النبي  صلى الله عليه وسلم  عاد رجلا فقال ‏\"‏ ما تشتهي ‏\"‏ ‏.‏ قال أشتهي خبز بر ‏.‏ قال النبي  صلى الله عليه وسلم  ‏\"‏ من كان عنده خبز بر فليبعث إلى أخيه ‏\"‏ ثم قال النبي  صلى الله عليه وسلم  ‏\"‏ إذا اشتهى مريض أحدكم شيئا فليطعمه ‏\"‏ ‏.‏",
      "text_en": " It wasnarrated from Ibn ‘Abbas that the Prophet (ﷺ) visited a manandsaid:                      “What do you long for?” He said: “I long for wheatbread.”The Prophet (ﷺ) said: “Whoever has any wheat bread, lethim send itto his brother.” Then the Prophet 9saw) said: “If anysick personamong you longs for something, then feed him.”",
      "usc_msa_ref": "",
      "chain": [
        "30115",
        "24213",
        "11023",
        "17"
      ],
      "source_display": {
        "en": "Sunan Ibn Majah",
        "ar": "سنن ابن ماجه",
        "ckb": "سونەنی ئیبن ماجە"
      }
    },
    {
      "id": "sunan-ibn-majah-3566",
      "hadith_no": "3566",
      "source": "Sunan Ibn Majah",
      "chapter": "Chapters on Medicine - كتاب الطب",
      "chapter_no": "31",
      "text_ar": "حدثنا الحسن بن علي الخلال، حدثنا صفوان بن هبيرة، حدثنا أبو مكين، عن عكرمة، عن ابن عباس، أن النبي  صلى الله عليه وسلم  عاد رجلا فقال له ‏\"‏ ما تشتهي ‏\"‏ ‏.‏ فقال أشتهي خبز بر ‏.‏ فقال النبي  صلى الله عليه وسلم  ‏\"‏ من كان عنده خبز بر فليبعث إلى أخيه ‏\"‏ ‏.‏ ثم قال النبي  صلى الله عليه وسلم  ‏\"‏ إذا اشتهى مريض أحدكم شيئا فليطعمه ‏\"‏ ‏.‏",
      "text_en": " It wasnarrated from Ibn ‘Abbas that the Prophet (ﷺ) visited a man(whowas sick) and said to him:                      “What do you desire?” He said: “Iwantwheat bread.” The Prophet (ﷺ) said: “Whoever has wheatbread, lethim send it to his brother.” Then the Prophet (ﷺ)said: “When a sickperson among you desires something, give it tohim.”",
      "usc_msa_ref": "",
      "chain": [
        "30115",
        "24213",
        "11023",
        "17"
      ],
      "source_display": {
        "en": "Sunan Ibn Majah",
        "ar": "سنن ابن ماجه",
        "ckb": "سونەنی ئیبن ماجە"
      }
    }
  ],
  "total_hadiths": 2,
  "grade_display": {
    "en": "Successor (Taba' Tabi') [9th Generation]",
    "ar": "تابع التابعين [الجيل التاسع]",
    "ckb": "شوێنكەوتووی شوێنكەوتوو [نەوەی نۆیەم]"
  }
}