{
  "id": "24371",
  "name": "al-Qasim bin al-Hakam bin Aws القاسم بن الحكم بن أوس",
  "full_name": "al-Qasim bin al-Hakam bin Aws القاسم بن الحكم بن أوس",
  "grade": "Succ. (Taba' Tabi') [9th generation]",
  "biography": {
    "birth": {
      "date_hijri": "NA",
      "date_gregorian": "NA",
      "date_display": [],
      "place": "Medina"
    },
    "death": {
      "date_hijri": "NA",
      "date_gregorian": "NA",
      "date_display": null,
      "place": "",
      "reason": "Natural"
    },
    "places_of_stay": [
      "al-Basra"
    ],
    "area_of_interest": [
      "Narrator[Grade:Maqbool] [ تمييز  -  لين الحديث ]"
    ],
    "tags": [
      "Ansar",
      "al-Basri"
    ]
  },
  "parents": [],
  "spouses": [],
  "siblings": [],
  "children": [],
  "teachers": [
    {
      "id": "12627",
      "name": "Abu 'Aabadh al-Zrqy أبو عبادة الزرقي",
      "grade": "Follower(Tabi') [3rd Generation]"
    },
    {
      "id": "20115",
      "name": "Ma'mar bin Rashid معمر بن راشد",
      "grade": "Succ. (Taba' Tabi') [7th generation]"
    }
  ],
  "students": [
    {
      "id": "30024",
      "name": "'Ubaidullah bin 'Umar al-Qawariri عبيد الله بن عمر القواريري",
      "grade": "3rd Century AH [10th generation]"
    },
    {
      "id": "30170",
      "name": "Muhammad bin al-Muthna - al-Zaman محمد بن المثنى أبو موسى - الزمن",
      "grade": "3rd Century AH [10th generation]"
    }
  ],
  "hadiths": [],
  "total_hadiths": 0
}