{
  "id": "24397",
  "name": "Muhammad bin Dhkwan محمد بن ذكوان",
  "full_name": "Muhammad bin Dhkwan محمد بن ذكوان",
  "grade": "Succ. (Taba' Tabi') [7th generation]",
  "reliability_grade": "Weak",
  "biography": {
    "birth": {
      "date_hijri": "NA",
      "date_gregorian": "NA",
      "date_display": null,
      "place": "NA"
    },
    "death": {
      "date_hijri": "NA",
      "date_gregorian": "NA",
      "date_display": null,
      "place": "",
      "reason": "Natural"
    },
    "places_of_stay": [
      "al-Basra"
    ],
    "area_of_interest": [
      "Narrator[Grade:Weak] [ ق  -  ضعيف ]"
    ],
    "tags": [
      "al-Azdi",
      "Client",
      "al-Basri"
    ]
  },
  "parents": [],
  "spouses": [],
  "siblings": [],
  "children": [],
  "teachers": [],
  "students": [],
  "hadiths": [
    {
      "id": "sunan-ibn-majah-365",
      "hadith_no": "365",
      "source": "Sunan Ibn Majah",
      "chapter": "The Book of Purification and its Sunnah - كتاب الطهارة وسننها",
      "chapter_no": "1",
      "text_ar": "حدثنا محمد بن عقيل بن خويلد، حدثني حفص بن عبد الله، حدثني إبراهيم بن طهمان، عن محمد بن ذكوان، عن يعلى بن حكيم، عن سعيد بن جبير، عن ابن عباس، قال عدل رسول الله  صلى الله عليه وسلم  إلى الشعب فبال حتى أني آوي له من فك وركيه حين بال ‏.‏",
      "text_en": " It was narrated that Ibn 'Abbas said:                     \"The Messenger of Allah turned towards a mountain pass and urinated, until I took pity on him because of the way he parted his legs when he urinated.\"",
      "usc_msa_ref": "",
      "chain": [
        "38552",
        "20420",
        "20187",
        "24397",
        "11567",
        "11050",
        "17"
      ]
    },
    {
      "id": "sunan-ibn-majah-2900",
      "hadith_no": "2900",
      "source": "Sunan Ibn Majah",
      "chapter": "The Chapters on Jihad - كتاب الجهاد",
      "chapter_no": "24",
      "text_ar": "حدثنا أبو بكر بن أبي شيبة، حدثنا يعلى بن عبيد، حدثنا حجاج بن دينار، عن محمد بن ذكوان، عن شهر بن حوشب، عن عمرو بن عبسة، قال أتيت النبي صلى الله عليه وسلم فقلت يا رسول الله أى الجهاد أفضل قال ‏\"‏ من أهريق دمه وعقر جواده ‏\"‏ ‏.‏",
      "text_en": " It wasnarrated that ‘Amr bin ‘Abasah said:                      “I came to the Prophet(ﷺ) and said: ‘O Messenger of Allah, which Jihad is best?’ Hesaid:‘(That of a man) whose blood is shed and his horse iswounded.’”",
      "usc_msa_ref": "",
      "chain": [
        "30201",
        "20372",
        "20737",
        "24397",
        "11044",
        "4002"
      ]
    }
  ],
  "total_hadiths": 2
}