{
  "id": "28205",
  "name": "Sa'id bin Abd al-Jabbar سعيد بن عبد الجبار الزبيدي",
  "full_name": "Sa'id bin Abd al-Jabbar سعيد بن عبد الجبار الزبيدي",
  "grade": "Succ. (Taba' Tabi') [8th generation]",
  "biography": {
    "birth": {
      "date_hijri": "NA",
      "date_gregorian": "NA",
      "date_display": null,
      "place": "NA"
    },
    "death": {
      "date_hijri": "NA",
      "date_gregorian": "NA",
      "date_display": null,
      "place": "",
      "reason": "Natural"
    },
    "places_of_stay": [
      "al-Hims"
    ],
    "area_of_interest": [
      "Narrator[Grade:Weak] [ ق  -  ضعيف ]"
    ],
    "tags": [
      "al-Zubaidi",
      "al-Himsi"
    ]
  },
  "parents": [],
  "spouses": [],
  "siblings": [],
  "children": [],
  "teachers": [
    {
      "id": "11065",
      "name": "Hisham bin 'Urwa هشام بن عروة",
      "grade": "Follower(Tabi') [5th generation]"
    },
    {
      "id": "28619",
      "name": "Wahshi bin Harb bin Wahshi وحشي بن حرب بن وحشي",
      "grade": "Succ. (Taba' Tabi') [8th generation]"
    },
    {
      "id": "27512",
      "name": "Rwh bin Jnah al-Amwy Mwlahm روح بن جناح",
      "grade": "Succ. (Taba' Tabi') [7th generation]"
    }
  ],
  "students": [
    {
      "id": "20644",
      "name": "Baqiyya bin al-Walid bin Sa'aid بقية بن الوليد بن صائد",
      "grade": "Succ. (Taba' Tabi') [8th generation]"
    },
    {
      "id": "20364",
      "name": "Yahya bin Aadm bin Sulaiman يحيى بن آدم بن سليمان",
      "grade": "Succ. (Taba' Tabi') [9th generation]"
    },
    {
      "id": "30161",
      "name": "Muhammad bin Abi Bakr bin 'Ali محمد بن أبي بكر بن علي بن عطاء المقدمي",
      "grade": "3rd Century AH [10th generation]"
    }
  ],
  "hadiths": [],
  "total_hadiths": 0
}