{
  "id": "38072",
  "name": "Abu Thaur al-Kalbi إبراهيم بن خالد أبو ثور الكلبي",
  "full_name": "Abu Thaur al-Kalbi إبراهيم بن خالد أبو ثور الكلبي",
  "grade": "3rd Century AH [10th generation]",
  "reliability_grade": "Thiqah",
  "biography": {
    "birth": {
      "date_hijri": "NA",
      "date_gregorian": "NA",
      "date_display": null,
      "place": "NA"
    },
    "death": {
      "date_hijri": "240",
      "date_gregorian": "NA",
      "date_display": null,
      "place": "",
      "reason": "Natural"
    },
    "places_of_stay": [
      "Baghdad"
    ],
    "area_of_interest": [
      "Narrator[Grade:Thiqah] [ د  ق  -  ثقة ]",
      "Fiqh"
    ],
    "tags": [
      "al-Kalbi"
    ],
    "area_of_interest_display": [
      {
        "en": "Narrator[Grade:Thiqah] [ د  ق  -  ثقة ]",
        "ar": "Narrator[Grade:Thiqah] [ د  ق  -  ثقة ]",
        "ckb": "Narrator[Grade:Thiqah] [ د  ق  -  ثقة ]"
      },
      {
        "en": "Fiqh",
        "ar": "فقه",
        "ckb": "فیقهـ"
      }
    ],
    "places_of_stay_display": [
      {
        "en": "Baghdad",
        "ar": "بغداد",
        "ckb": "بەغداد"
      }
    ],
    "tags_display": [
      {
        "en": "al-Kalbi",
        "ar": "al-Kalbi",
        "ckb": "al-Kalbi"
      }
    ]
  },
  "parents": [],
  "spouses": [],
  "siblings": [],
  "children": [],
  "teachers": [],
  "students": [],
  "hadiths": [
    {
      "id": "sunan-abi-daud-45",
      "hadith_no": "45",
      "source": "Sunan Abi Da'ud",
      "chapter": "Purification (Kitab Al-Taharah) - كتاب الطهارة",
      "chapter_no": "1",
      "text_ar": "حدثنا إبراهيم بن خالد، حدثنا أسود بن عامر، حدثنا شريك، وهذا، لفظه ح وحدثنا محمد بن عبد الله، - يعني المخرمي - حدثنا وكيع، عن شريك، عن إبراهيم بن جرير، عن المغيرة، عن أبي زرعة، عن أبي هريرة، قال كان النبي صلى الله عليه وسلم إذا أتى الخلاء أتيته بماء في تور أو ركوة فاستنجى ‏.‏ قال أبو داود في حديث وكيع ثم مسح يده على الأرض ثم أتيته بإناء آخر فتوضأ ‏.‏ قال أبو داود وحديث الأسود بن عامر أتم ‏.‏",
      "text_en": " Narrated Abu Hurayrah :                     When the Prophet (sal Allaahu alayhi wa sallam ) went to the privy, I took to him water in a small vessel  or a skin, and he cleansed himself. He then wiped his hand on the ground. I then took to him another vessel  and he performed ablution.Abu Dawud said : The tradition is transmitted by al-Aswad b. 'Amir is more perfect.",
      "usc_msa_ref": "",
      "chain": [
        "38072",
        "20380",
        "20587",
        "30271",
        "20032",
        "11858",
        "18002",
        "166",
        "30554",
        "13"
      ],
      "source_display": {
        "en": "Sunan Abi Da'ud",
        "ar": "سنن أبي داود",
        "ckb": "سونەنی ئەبی داود"
      }
    },
    {
      "id": "sunan-abi-daud-235",
      "hadith_no": "235",
      "source": "Sunan Abi Da'ud",
      "chapter": "Purification (Kitab Al-Taharah) - كتاب الطهارة",
      "chapter_no": "1",
      "text_ar": "حدثنا عمرو بن عثمان، حدثنا محمد بن حرب، حدثنا الزبيدي، ح وحدثنا عياش بن الأزرق، أخبرنا ابن وهب، عن يونس، ح وحدثنا مخلد بن خالد، حدثنا إبراهيم بن خالد، - إمام مسجد صنعاء - حدثنا رباح، عن معمر، ح وحدثنا مؤمل بن الفضل، حدثنا الوليد، عن الأوزاعي، كلهم عن الزهري، عن أبي سلمة، عن أبي هريرة، قال أقيمت الصلاة وصف الناس صفوفهم فخرج رسول الله صلى الله عليه وسلم حتى إذا قام في مقامه ذكر أنه لم يغتسل فقال للناس ‏\"‏ مكانكم ‏\"‏ ‏.‏ ثم رجع إلى بيته فخرج علينا ينطف رأسه وقد اغتسل ونحن صفوف ‏.‏ وهذا لفظ ابن حرب وقال عياش في حديثه فلم نزل قياما ننتظره حتى خرج علينا وقد اغتسل ‏.‏",
      "text_en": " Abu Hurairah reported:                      The prayer (in congregation) began and people stood in their rows. The Messenger of Allah (May peace be upon him) came out (from his residence). When he stood at his proper place he recalled that he did not take a bath. He then said to the people: (Remain standing) at your places. Then he returned to his house and came out upon us after taking a bath while the drops of water were coming down from his head. We were standing in the rows (of prayer). This is the version of Ibn Harb. ‘Ayyash reported in his version: we kept on waiting for him while we were standing until he came upon us after he had taken a bath.",
      "usc_msa_ref": "",
      "chain": [
        "10581",
        "30373",
        "20459",
        "20029",
        "20475",
        "30567",
        "38072",
        "20115",
        "38659",
        "20733",
        "20024",
        "11013",
        "10567"
      ],
      "source_display": {
        "en": "Sunan Abi Da'ud",
        "ar": "سنن أبي داود",
        "ckb": "سونەنی ئەبی داود"
      }
    },
    {
      "id": "sunan-abi-daud-309",
      "hadith_no": "309",
      "source": "Sunan Abi Da'ud",
      "chapter": "Purification (Kitab Al-Taharah) - كتاب الطهارة",
      "chapter_no": "1",
      "text_ar": "حدثنا إبراهيم بن خالد، حدثنا معلى بن منصور، عن علي بن مسهر، عن الشيباني، عن عكرمة، قال كانت أم حبيبة تستحاض فكان زوجها يغشاها ‏.‏ قال أبو داود وقال يحيى بن معين معلى ثقة ‏.‏ وكان أحمد بن حنبل لا يروي عنه لأنه كان ينظر في الرأى ‏.‏",
      "text_en": " 'Ikrimah said:                      Umm Habibah had a prolonged flow of blood ; her husband used to cohabit with her.Abu Dawud said: Yahya b. Ma'in has pronounced Mu'alla (a narrator of this tradition) as trustworthy. But Ahmad b. Hanbal would not report (traditions) from him because he exercised personal opinion.",
      "usc_msa_ref": "",
      "chain": [
        "38072",
        "30278",
        "20345",
        "11352",
        "11023",
        "72"
      ],
      "source_display": {
        "en": "Sunan Abi Da'ud",
        "ar": "سنن أبي داود",
        "ckb": "سونەنی ئەبی داود"
      }
    },
    {
      "id": "sunan-abi-daud-1324",
      "hadith_no": "1324",
      "source": "Sunan Abi Da'ud",
      "chapter": "Voluntary Prayers - كتاب التطوع",
      "chapter_no": "5",
      "text_ar": "حدثنا مخلد بن خالد، حدثنا إبراهيم، - يعني ابن خالد - عن رباح بن زيد، عن معمر، عن أيوب، عن ابن سيرين، عن أبي هريرة، قال ‏:‏ ‏\"‏ إذا ‏\"‏ ‏.‏ بمعناه زاد ‏:‏ ‏\"‏ ثم ليطول بعد ما شاء ‏\"‏ ‏.‏ قال أبو داود ‏:‏ روى هذا الحديث حماد بن سلمة وزهير بن معاوية وجماعة عن هشام عن محمد أوقفوه على أبي هريرة، وكذلك رواه أيوب وابن عون أوقفوه على أبي هريرة، ورواه ابن عون عن محمد قال ‏:‏ فيهما تجوز ‏.‏",
      "text_en": " This tradition has also been transmitted by Abu Hurairah through a different chain of narrators to the same effect. This version adds:                      He should then prolong it afterwards as much as he likes.Abu Dawud said: This tradition has been transmitted by Hammad b. Salamah, Zuhair b. Mu'awiyah and a group of narrators from Hisham. They transmitted it as a statement of Abu Hurairah himself (mauquf).This tradition has also been transmitted by Ibn 'Awn from Muhammad (b. Sirin). This version has the wordings: These two rak'ahs were short.",
      "usc_msa_ref": "",
      "chain": [
        "30567",
        "38072",
        "28175",
        "20115",
        "11015",
        "11035",
        "13",
        "20021"
      ],
      "source_display": {
        "en": "Sunan Abi Da'ud",
        "ar": "سنن أبي داود",
        "ckb": "سونەنی ئەبی داود"
      }
    },
    {
      "id": "sunan-abi-daud-2206",
      "hadith_no": "2206",
      "source": "Sunan Abi Da'ud",
      "chapter": "Divorce (Kitab Al-Talaq) - كتاب الطلاق",
      "chapter_no": "13",
      "text_ar": "حدثنا ابن السرح، وإبراهيم بن خالد الكلبي أبو ثور، - في آخرين - قالوا حدثنا محمد بن إدريس الشافعي، حدثني عمي، محمد بن علي بن شافع عن عبد الله بن علي بن السائب، عن نافع بن عجير بن عبد يزيد بن ركانة، أن ركانة بن عبد يزيد، طلق امرأته سهيمة البتة فأخبر النبي صلى الله عليه وسلم بذلك وقال والله ما أردت إلا واحدة ‏.‏ فقال رسول الله صلى الله عليه وسلم ‏\"‏ والله ما أردت إلا واحدة ‏\"‏ ‏.‏ فقال ركانة والله ما أردت إلا واحدة ‏.‏ فردها إليه رسول الله صلى الله عليه وسلم فطلقها الثانية في زمان عمر والثالثة في زمان عثمان ‏.‏ قال أبو داود أوله لفظ إبراهيم وآخره لفظ ابن السرح ‏.‏",
      "text_en": " Nafi' bun Ujair bin Abd Yazid bin Ruknah reported Ruknah bin ‘Abd Yazid divorced his wife Suhaimah absolutely. The Prophet (ﷺ) was informed about this matter. He said to him (the Prophet) I swear by Allaah that I meant it to be only a single utterance of divorce. The Apostle of Allaah(ﷺ) said “I swear by Allaah that I meant it to be only a single divorce. The Apostle of Allaah(ﷺ) restored her to him, Then he divorced her the second time in the time of ‘Umar and the third time of ‘Uthman.Abu Dawud said “This tradition contains the words of Ibrahim in its beginning and the words of Ibn Al Sarh in the end.",
      "usc_msa_ref": "",
      "chain": [
        "30485",
        "38072",
        "20002",
        "18548",
        "947"
      ],
      "source_display": {
        "en": "Sunan Abi Da'ud",
        "ar": "سنن أبي داود",
        "ckb": "سونەنی ئەبی داود"
      }
    },
    {
      "id": "sunan-abi-daud-3501",
      "hadith_no": "3501",
      "source": "Sunan Abi Da'ud",
      "chapter": "Wages (Kitab Al-Ijarah) - كتاب الإجارة",
      "chapter_no": "24",
      "text_ar": "حدثنا محمد بن عبد الله الأرزي، وإبراهيم بن خالد أبو ثور الكلبي، - المعنى - قالا حدثنا عبد الوهاب، - قال محمد عبد الوهاب بن عطاء - أخبرنا سعيد، عن قتادة، عن أنس بن مالك، أن رجلا، على عهد رسول الله صلى الله عليه وسلم كان يبتاع وفي عقدته ضعف فأتى أهله نبي الله صلى الله عليه وسلم فقالوا يا نبي الله احجر على فلان فإنه يبتاع وفي عقدته ضعف فدعاه النبي صلى الله عليه وسلم فنهاه عن البيع فقال يا نبي الله إني لا أصبر عن البيع ‏.‏ فقال رسول الله صلى الله عليه وسلم ‏\"‏ إن كنت غير تارك البيع فقل هاء وهاء ولا خلابة ‏\"‏ ‏.‏ قال أبو ثور عن سعيد ‏.‏",
      "text_en": " Narrated Anas ibn Malik:                     During the time of the Messenger of Allah (ﷺ) a man used to buy (goods), and he was weak in his intellect. His people came to the Prophet of Allah (ﷺ) and said: Prophet of Allah, stop so-and-so (to make a bargain) for he buys (goods), but he is weak in his intellect. So the Prophet (ﷺ) called on him and forbade him to make a bargain. He said: Prophet of Allah, I cannot keep away myself from business transactions. Thereupon the Messenger of Allah (ﷺ) said: If you cannot give up making a bargain , then say: Take , and give, and there is no attempt to deceive.",
      "usc_msa_ref": "",
      "chain": [
        "38072",
        "20259",
        "11168",
        "11019",
        "19"
      ],
      "source_display": {
        "en": "Sunan Abi Da'ud",
        "ar": "سنن أبي داود",
        "ckb": "سونەنی ئەبی داود"
      }
    },
    {
      "id": "sunan-abi-daud-3799",
      "hadith_no": "3799",
      "source": "Sunan Abi Da'ud",
      "chapter": "Foods (Kitab Al-At'imah) - كتاب الأطعمة",
      "chapter_no": "28",
      "text_ar": "حدثنا إبراهيم بن خالد الكلبي أبو ثور، حدثنا سعيد بن منصور، حدثنا عبد العزيز بن محمد، عن عيسى بن نميلة، عن أبيه، قال كنت عند ابن عمر فسئل عن أكل القنفذ، فتلا ‏{‏ قل لا أجد فيما أوحي إلى محرما ‏}‏ الآية قال قال شيخ عنده سمعت أبا هريرة يقول ذكر عند النبي صلى الله عليه وسلم فقال ‏\"‏ خبيثة من الخبائث ‏\"‏ ‏.‏ فقال ابن عمر إن كان قال رسول الله صلى الله عليه وسلم هذا فهو كما قال ما لم ندر ‏.‏",
      "text_en": " Narrated Abdullah ibn Umar:                     Numaylah  said: I was with Ibn Umar. He was asked about eating hedgehog. He recited: \"Say: I find not in the message received by me by inspiration any (meat) forbidden.\" An old man who was with him said: I heard AbuHurayrah say: It was mentioned to the Messenger of Allah (ﷺ). Noxious of the noxious. Ibn Umar said: If the Messenger of Allah (ﷺ) had said it, it is as he said that we did not know.",
      "usc_msa_ref": "",
      "chain": [
        "38072",
        "30116",
        "20167",
        "13"
      ],
      "source_display": {
        "en": "Sunan Abi Da'ud",
        "ar": "سنن أبي داود",
        "ckb": "سونەنی ئەبی داود"
      }
    },
    {
      "id": "sunan-abi-daud-4037",
      "hadith_no": "4037",
      "source": "Sunan Abi Da'ud",
      "chapter": "Clothing (Kitab Al-Libas) - كتاب اللباس",
      "chapter_no": "34",
      "text_ar": "حدثنا إبراهيم بن خالد أبو ثور الكلبي، حدثنا عمر بن يونس بن القاسم اليمامي، حدثنا عكرمة بن عمار، حدثنا أبو زميل، حدثني عبد الله بن عباس، قال لما خرجت الحرورية أتيت عليا - رضى الله عنه - فقال ائت هؤلاء القوم ‏.‏ فلبست أحسن ما يكون من حلل اليمن - قال أبو زميل وكان ابن عباس رجلا جميلا جهيرا - قال ابن عباس فأتيتهم فقالوا مرحبا بك يا ابن عباس ما هذه الحلة قال ما تعيبون على لقد رأيت على رسول الله صلى الله عليه وسلم أحسن ما يكون من الحلل ‏.‏ قال أبو داود اسم أبي زميل سماك بن الوليد الحنفي ‏.‏",
      "text_en": " Narrated Abdullah ibn Abbas:                     When the Haruriyyah made a revolt, I came to Ali (may Allah be pleased with him). He said: Go to these people. I then put on the best suit of the Yemen. AbuZumayl (a transmitter) said: Ibn Abbas was handsome and of imposing countenance. Ibn Abbas said: I then came to them and they said: Welcome to you, Ibn Abbas! what is this suit of clothes? I said: Why are you objecting to me? I saw over the Messenger of Allah (ﷺ) the best suit of clothes.Abu Dawud said: The name of Abu Zumail is Sammak b. al-Walid al-Hanafi.",
      "usc_msa_ref": "",
      "chain": [
        "38072",
        "20450",
        "10704",
        "17"
      ],
      "source_display": {
        "en": "Sunan Abi Da'ud",
        "ar": "سنن أبي داود",
        "ckb": "سونەنی ئەبی داود"
      }
    },
    {
      "id": "sunan-abi-daud-4514",
      "hadith_no": "4514",
      "source": "Sunan Abi Da'ud",
      "chapter": "Types of Blood-Wit (Kitab Al-Diyat) - كتاب الديات",
      "chapter_no": "41",
      "text_ar": "حدثنا أحمد بن حنبل، حدثنا إبراهيم بن خالد، حدثنا رباح، عن معمر، عن الزهري، عن عبد الرحمن بن عبد الله بن كعب بن مالك، عن أمه، أن أم مبشر، - قال أبو سعيد بن الأعرابي كذا قال عن أمه، والصواب، عن أبيه، عن أم مبشر، - دخلت على النبي صلى الله عليه وسلم فذكر معنى حديث مخلد بن خالد نحو حديث جابر قال فمات بشر بن البراء بن معرور فأرسل إلى اليهودية فقال ‏\"‏ ما حملك على الذي صنعت ‏\"‏ ‏.‏ فذكر نحو حديث جابر فأمر بها رسول الله صلى الله عليه وسلم فقتلت ولم يذكر الحجامة ‏.‏",
      "text_en": " Narrated 'Abd al-Rahman b. 'Abd Allah b. Ka'b b. Malik :                     On the authority of his mother than Umm Mubashshir said (Abu Sa'id b. al-A'rabi said: So he said it on the authority of his mother ; what is correct is: on the authority of his father, instead of his mother): I entered upon the Prophet (ﷺ). He then mentioned the tradition of Makhlad b. Khalid in a way similar to the tradition of Jabir. The narrator said: Then Bishr b. al-Bara' b. Ma'rur died. So he (the Prophet) sent for the Jewess and said: What did motivate you for your work you have done ? He (the narrator) then mentioned the rest of the tradition like the tradition of Jabir. The Messenger of Allah (ﷺ) ordered regarding her and she was killed. He (the narrator in this version) did not mention cupping.",
      "usc_msa_ref": "",
      "chain": [
        "30007",
        "38072",
        "20115",
        "11013",
        "11519",
        "1293"
      ],
      "source_display": {
        "en": "Sunan Abi Da'ud",
        "ar": "سنن أبي داود",
        "ckb": "سونەنی ئەبی داود"
      }
    },
    {
      "id": "sunan-abi-daud-4784",
      "hadith_no": "4784",
      "source": "Sunan Abi Da'ud",
      "chapter": "General Behavior (Kitab Al-Adab) - كتاب الأدب",
      "chapter_no": "43",
      "text_ar": "حدثنا بكر بن خلف، والحسن بن علي، - المعنى - قالا حدثنا إبراهيم بن خالد، حدثنا أبو وائل القاص، قال دخلنا على عروة بن محمد بن السعدي فكلمه رجل فأغضبه فقام فتوضأ ثم رجع وقد توضأ فقال حدثني أبي عن جدي عطية قال قال رسول الله صلى الله عليه وسلم ‏\"‏ إن الغضب من الشيطان وإن الشيطان خلق من النار وإنما تطفأ النار بالماء فإذا غضب أحدكم فليتوضأ ‏\"‏ ‏.‏",
      "text_en": " Narrated Atiyyah as-Sa'di:                     AbuWa'il al-Qass said: We entered upon Urwah ibn Muhammad ibn as-Sa'di. A man spoke to him and made him angry. So he stood and performed ablution; he then returned and performed ablution, and said: My father told me on the authority of my grandfather Atiyyah who reported the Messenger of Allah (ﷺ) as saying: Anger comes from the devil, the devil was created of fire, and fire is extinguished only with water; so when one of you becomes angry, he should perform ablution.",
      "usc_msa_ref": "",
      "chain": [
        "34043",
        "30",
        "38072",
        "28278"
      ],
      "source_display": {
        "en": "Sunan Abi Da'ud",
        "ar": "سنن أبي داود",
        "ckb": "سونەنی ئەبی داود"
      }
    },
    {
      "id": "sunan-an-nasai-958",
      "hadith_no": "958",
      "source": "Sunan an-Nasa'i",
      "chapter": "The Book of the Commencement of the Prayer - كتاب الافتتاح",
      "chapter_no": "11",
      "text_ar": "أخبرنا عبد الملك بن عبد الحميد بن ميمون بن مهران، قال حدثنا ابن حنبل، قال حدثنا إبراهيم بن خالد، قال حدثنا رباح، عن معمر، عن ابن طاوس، عن عكرمة بن خالد، عن جعفر بن المطلب بن أبي وداعة، عن أبيه، قال قرأ رسول الله صلى الله عليه وسلم بمكة سورة النجم فسجد وسجد من عنده فرفعت رأسي وأبيت أن أسجد ولم يكن يومئذ أسلم المطلب ‏.‏",
      "text_en": " It was narrated from Ja'far bin Al-Muttalib bin Abi Wada'ah that:                     His father said: \"The Messenger of Allah (ﷺ) recited Surat An-Najm in Makkah and prostrated, and those who were with him prostrated. I raised my head and refused to prostrate.\" At that time Al-Muttalib had not yet accepted Islam.",
      "usc_msa_ref": "",
      "chain": [
        "38072",
        "20115",
        "11433",
        "11709",
        "2018"
      ],
      "source_display": {
        "en": "Sunan an-Nasa'i",
        "ar": "سنن النسائي",
        "ckb": "سونەنی نەسائی"
      }
    },
    {
      "id": "sunan-an-nasai-Grade-66",
      "hadith_no": "Grade",
      "source": "Sunan an-Nasa'i",
      "chapter": "The Book of Jumu'ah (Friday Prayer) - كتاب الجمعة",
      "chapter_no": "14",
      "text_ar": "أخبرني محمد بن يحيى بن عبد الله، قال حدثنا أحمد بن حنبل، قال حدثنا إبراهيم بن خالد، عن رباح، عن معمر، عن الزهري، قال حدثني سعيد، عن أبي هريرة، عن رسول الله صلى الله عليه وسلم قال ‏\"‏ إن في الجمعة ساعة لا يوافقها عبد مسلم يسأل الله فيها شيئا إلا أعطاه إياه ‏\"‏ ‏.‏",
      "text_en": " It was narrated from Abu Hurairah that:                     The Messenger of Allah (ﷺ) said: \"On Friday, there is an hour when, if a Muslim slave asks Allah (SWT) for something at that time, He will give it to him.\"",
      "usc_msa_ref": "",
      "chain": [
        "11222",
        "30007",
        "38072",
        "20115",
        "11013",
        "11168",
        "13"
      ],
      "source_display": {
        "en": "Sunan an-Nasa'i",
        "ar": "سنن النسائي",
        "ckb": "سونەنی نەسائی"
      }
    },
    {
      "id": "sunan-ibn-majah-1051",
      "hadith_no": "1051",
      "source": "Sunan Ibn Majah",
      "chapter": "Establishing the Prayer and the Sunnah Regarding Them - كتاب إقامة الصلاة والسنة فيها",
      "chapter_no": "5",
      "text_ar": "حدثنا أبو ثور، إبراهيم بن خالد حدثنا أبو قطن، حدثنا شعبة، عن قتادة، عن خلاس، عن أبي رافع، عن أبي هريرة، قال قال رسول الله  صلى الله عليه وسلم  ‏\"‏ لو يعلمون ما في الصف الأول لكانت قرعة ‏\"‏ ‏.‏",
      "text_en": " It wasnarrated that Abu Hurairah said:                      “The Messenger of Allah (ﷺ)said: ‘If they knew what (goodness) there is in the first row, theywould cast lots for it.’”",
      "usc_msa_ref": "",
      "chain": [
        "38072",
        "20563",
        "20020",
        "11019",
        "11283",
        "479",
        "13"
      ],
      "source_display": {
        "en": "Sunan Ibn Majah",
        "ar": "سنن ابن ماجه",
        "ckb": "سونەنی ئیبن ماجە"
      }
    }
  ],
  "total_hadiths": 13,
  "grade_display": {
    "en": "3rd Century AH [10th Generation]",
    "ar": "القرن الثالث الهجري [الجيل العاشر]",
    "ckb": "سەدەی سێیەمی كۆچی [نەوەی دەیەم]"
  }
}